grid_async_task/__init__.py
grid_async_task/config/__init__.py
grid_async_task/config/settings.py
grid_async_task/core/__init__.py
grid_async_task/core/database_manager.py
grid_async_task/core/notification_manager.py
grid_async_task/core/task_handler.py
grid_async_task/core/task_processor.py
grid_async_task/core/task_producer.py
grid_async_task-1.0.10.dist-info/METADATA
grid_async_task-1.0.10.dist-info/WHEEL
grid_async_task-1.0.10.dist-info/top_level.txt
grid_async_task-1.0.10.dist-info/RECORD
