Metadata-Version: 2.4
Name: grid-async-task
Version: 1.0.10
Summary: 一个通用的异步任务处理插件，支持RabbitMQ队列监听、任务重试、进度通知等功能
Home-page: https://gitee.com/shenzhen-grid/grid-async-task-plugin
Author: grid
Author-email: grid <grid@example.com>
License-Expression: MIT
Project-URL: Homepage, https://github.com/your-username/grid-async-task-plugin
Project-URL: Bug Reports, https://github.com/your-username/grid-async-task-plugin/issues
Project-URL: Source, https://github.com/your-username/grid-async-task-plugin
Keywords: async,task,rabbitmq,queue,celery,kubernetes,keda
Classifier: Development Status :: 4 - Beta
Classifier: Intended Audience :: Developers
Classifier: Operating System :: OS Independent
Classifier: Programming Language :: Python :: 3
Classifier: Programming Language :: Python :: 3.8
Classifier: Programming Language :: Python :: 3.9
Classifier: Programming Language :: Python :: 3.10
Classifier: Programming Language :: Python :: 3.11
Classifier: Programming Language :: Python :: 3.12
Classifier: Topic :: Software Development :: Libraries :: Python Modules
Classifier: Topic :: System :: Distributed Computing
Requires-Python: >=3.8
Requires-Dist: pika>=1.3.0
Requires-Dist: PyMySQL>=1.0.2
Requires-Dist: SQLAlchemy>=1.4.0
Requires-Dist: python-dotenv>=0.19.0
Requires-Dist: requests>=2.25.0
Requires-Dist: aiohttp>=3.8.0
Requires-Dist: loguru>=0.6.0
Requires-Dist: pydantic>=1.8.0
Requires-Dist: pydantic-settings>=2.0.0
Requires-Dist: tenacity>=8.0.0
Requires-Dist: click>=8.0.0
Provides-Extra: dev
Requires-Dist: pytest>=6.0; extra == "dev"
Requires-Dist: pytest-asyncio>=0.18.0; extra == "dev"
Requires-Dist: black>=22.0; extra == "dev"
Requires-Dist: isort>=5.0; extra == "dev"
Requires-Dist: flake8>=4.0; extra == "dev"
Dynamic: author
Dynamic: home-page
Dynamic: requires-python
